i2i/__init__.py
i2i/cli.py
i2i/config.py
i2i/consensus.py
i2i/epistemic.py
i2i/protocol.py
i2i/providers.py
i2i/router.py
i2i/schema.py
i2i/search.py
i2i/verification.py
i2i_mcip-0.1.0.dist-info/METADATA
i2i_mcip-0.1.0.dist-info/WHEEL
i2i_mcip-0.1.0.dist-info/entry_points.txt
i2i_mcip-0.1.0.dist-info/licenses/LICENSE
i2i_mcip-0.1.0.dist-info/RECORD
