Metadata-Version: 2.4
Name: i2i-mcip
Version: 0.1.0
Summary: AI-to-AI Communication Protocol - Multi-model consensus, verification, and intelligent routing
Project-URL: Homepage, https://github.com/lancejames221b/i2i
Project-URL: Documentation, https://github.com/lancejames221b/i2i#readme
Project-URL: Repository, https://github.com/lancejames221b/i2i
Project-URL: Issues, https://github.com/lancejames221b/i2i/issues
Author-email: Lance James <lance@unit221b.com>
License: MIT
License-File: LICENSE
Keywords: ai,ai-to-ai,consensus,llm,mcip,multi-model,protocol
Classifier: Development Status :: 4 - Beta
Classifier: Intended Audience :: Developers
Classifier: License :: OSI Approved :: MIT License
Classifier: Programming Language :: Python :: 3
Classifier: Programming Language :: Python :: 3.9
Classifier: Programming Language :: Python :: 3.10
Classifier: Programming Language :: Python :: 3.11
Classifier: Programming Language :: Python :: 3.12
Classifier: Programming Language :: Python :: 3.13
Classifier: Topic :: Scientific/Engineering :: Artificial Intelligence
Requires-Python: >=3.9
Requires-Dist: aiohttp>=3.9.0
Requires-Dist: anthropic>=0.18.0
Requires-Dist: cohere>=4.0.0
Requires-Dist: google-generativeai>=0.3.0
Requires-Dist: groq>=0.4.0
Requires-Dist: mistralai>=0.1.0
Requires-Dist: numpy>=1.24.0
Requires-Dist: openai>=1.0.0
Requires-Dist: pydantic>=2.0.0
Requires-Dist: python-dotenv>=1.0.0
Requires-Dist: rich>=13.0.0
Requires-Dist: typer>=0.9.0
Provides-Extra: dev
Requires-Dist: black>=24.0.0; extra == 'dev'
Requires-Dist: pytest-asyncio>=0.23.0; extra == 'dev'
Requires-Dist: pytest-cov>=4.0.0; extra == 'dev'
Requires-Dist: pytest-mock>=3.12.0; extra == 'dev'
Requires-Dist: pytest>=8.0.0; extra == 'dev'
Requires-Dist: respx>=0.21.0; extra == 'dev'
Requires-Dist: ruff>=0.1.0; extra == 'dev'
